socketlabs/__init__.py
socketlabs/injectionapi/__imports__.py
socketlabs/injectionapi/__init__.py
socketlabs/injectionapi/addressresult.py
socketlabs/injectionapi/proxy.py
socketlabs/injectionapi/retrysettings.py
socketlabs/injectionapi/sendresponse.py
socketlabs/injectionapi/sendresult.py
socketlabs/injectionapi/socketlabsclient.py
socketlabs/injectionapi/version.py
socketlabs/injectionapi/core/__init__.py
socketlabs/injectionapi/core/apikeyparser.py
socketlabs/injectionapi/core/apikeyparseresult.py
socketlabs/injectionapi/core/httpendpoint.py
socketlabs/injectionapi/core/httprequest.py
socketlabs/injectionapi/core/injectionrequestfactory.py
socketlabs/injectionapi/core/injectionresponseparser.py
socketlabs/injectionapi/core/retryhandler.py
socketlabs/injectionapi/core/sendvalidator.py
socketlabs/injectionapi/core/stringextension.py
socketlabs/injectionapi/core/serialization/__init__.py
socketlabs/injectionapi/core/serialization/addressjson.py
socketlabs/injectionapi/core/serialization/attachmentjson.py
socketlabs/injectionapi/core/serialization/customheaderjson.py
socketlabs/injectionapi/core/serialization/injectionrequest.py
socketlabs/injectionapi/core/serialization/injectionresponsedto.py
socketlabs/injectionapi/core/serialization/mergedatajson.py
socketlabs/injectionapi/core/serialization/mergefieldjson.py
socketlabs/injectionapi/core/serialization/messagejson.py
socketlabs/injectionapi/core/serialization/messageresultdto.py
socketlabs/injectionapi/core/serialization/metadatajson.py
socketlabs/injectionapi/message/__imports__.py
socketlabs/injectionapi/message/__init__.py
socketlabs/injectionapi/message/attachment.py
socketlabs/injectionapi/message/basicmessage.py
socketlabs/injectionapi/message/bulkmessage.py
socketlabs/injectionapi/message/bulkrecipient.py
socketlabs/injectionapi/message/customheader.py
socketlabs/injectionapi/message/emailaddress.py
socketlabs/injectionapi/message/messagebase.py
socketlabs/injectionapi/message/metadata.py
socketlabs_injectionapi-1.4.3.dist-info/LICENSE.md
socketlabs_injectionapi-1.4.3.dist-info/METADATA
socketlabs_injectionapi-1.4.3.dist-info/WHEEL
socketlabs_injectionapi-1.4.3.dist-info/top_level.txt
socketlabs_injectionapi-1.4.3.dist-info/RECORD
