Metadata-Version: 2.1
Name: socketlabs-injectionapi
Version: 1.4.3
Summary: SocketLabs Email Delivery Python client library
Home-page: https://github.com/socketlabs/socketlabs-python
Author: David Schrenker, Matt Reibach, Ryan Lydzinski, Praneeth Chandra
Author-email: support@socketlabs.com
License: MIT
Project-URL: Organization, https://github.com/socketlabs
Project-URL: Bug Reports, https://github.com/socketlabs/socketlabs-python/issues
Project-URL: Source, https://github.com/socketlabs/socketlabs-python
Project-URL: License, https://github.com/socketlabs/socketlabs-python/blob/master/LICENSE
Classifier: Programming Language :: Python :: 3.4
Classifier: Programming Language :: Python :: 3.5
Classifier: Programming Language :: Python :: 3.6
Classifier: Programming Language :: Python :: 3.7
Classifier: Programming Language :: Python :: 3.8
Classifier: Programming Language :: Python :: 3.9
Classifier: License :: OSI Approved :: MIT License
Classifier: Operating System :: OS Independent
License-File: LICENSE.md
